caio/__init__.py
caio/abstract.py
caio/asyncio_base.py
caio/linux_aio.c
caio/linux_aio.pyi
caio/linux_aio_asyncio.py
caio/py.typed
caio/python_aio.py
caio/python_aio_asyncio.py
caio/thread_aio.c
caio/thread_aio.cpython-39-darwin.so
caio/thread_aio.pyi
caio/thread_aio_asyncio.py
caio/version.py
caio/src/threadpool/README.md
caio/src/threadpool/threadpool.c
caio/src/threadpool/threadpool.h
caio-0.9.23.dist-info/licenses/COPYING
caio-0.9.23.dist-info/METADATA
caio-0.9.23.dist-info/WHEEL
caio-0.9.23.dist-info/top_level.txt
caio-0.9.23.dist-info/RECORD
