Metadata-Version: 2.4
Name: caio
Version: 0.9.23
Summary: Asynchronous file IO for Linux MacOS or Windows.
Author-email: Dmitry Orlov <me@mosquito.su>
Project-URL: Source Code, https://github.com/mosquito/caio/
Classifier: Topic :: Software Development
Classifier: Topic :: Software Development :: Libraries
Classifier: Intended Audience :: Developers
Classifier: Natural Language :: English
Classifier: Operating System :: MacOS
Classifier: Operating System :: POSIX
Classifier: Operating System :: Microsoft
Classifier: Programming Language :: Python
Classifier: Programming Language :: Python :: 3
Classifier: Programming Language :: Python :: 3.9
Classifier: Programming Language :: Python :: 3.10
Classifier: Programming Language :: Python :: 3.11
Classifier: Programming Language :: Python :: 3.12
Classifier: Programming Language :: Python :: 3.13
Classifier: Programming Language :: Python :: Implementation :: CPython
Requires-Python: >=3.9
License-File: COPYING
Provides-Extra: develop
Requires-Dist: aiomisc-pytest; extra == "develop"
Requires-Dist: coveralls; extra == "develop"
Requires-Dist: pylama[toml]; extra == "develop"
Requires-Dist: pytest; extra == "develop"
Requires-Dist: pytest-cov; extra == "develop"
Requires-Dist: setuptools; extra == "develop"
Dynamic: license-file
